dykes/__init__.py
dykes/internal.py
dykes/options.py
dykes/processing.py
dykes/py.typed
dykes/utils.py
dykes-0.4.0.dist-info/LICENSE.txt
dykes-0.4.0.dist-info/METADATA
dykes-0.4.0.dist-info/WHEEL
dykes-0.4.0.dist-info/RECORD
