Metadata-Version: 2.3
Name: dykes
Version: 0.4.0
Summary: A tiny declarative Argparse wrapper.
License: MIT
Author: Piper Thunstrom
Author-email: pathunstrom@gmail.com
Requires-Python: >=3.12,<4.0
Classifier: License :: OSI Approved :: MIT License
Classifier: Programming Language :: Python :: 3
Classifier: Programming Language :: Python :: 3.12
Classifier: Programming Language :: Python :: 3.13
